retab/__init__.py
retab/_resource.py
retab/client.py
retab/generate_types.py
retab/py.typed
retab/resources/__init__.py
retab/resources/models.py
retab/resources/schemas.py
retab/resources/documents/__init__.py
retab/resources/documents/client.py
retab/resources/edit/__init__.py
retab/resources/edit/client.py
retab/resources/edit/agent/__init__.py
retab/resources/edit/agent/client.py
retab/resources/edit/templates/__init__.py
retab/resources/edit/templates/client.py
retab/resources/extractions/__init__.py
retab/resources/extractions/client.py
retab/resources/jobs/__init__.py
retab/resources/jobs/client.py
retab/resources/projects/__init__.py
retab/resources/projects/client.py
retab/resources/workflows/__init__.py
retab/resources/workflows/client.py
retab/resources/workflows/runs/__init__.py
retab/resources/workflows/runs/client.py
retab/types/__init__.py
retab/types/chat.py
retab/types/inference_settings.py
retab/types/jobs.py
retab/types/mime.py
retab/types/modality.py
retab/types/pagination.py
retab/types/standards.py
retab/types/documents/__init__.py
retab/types/documents/classify.py
retab/types/documents/correct_orientation.py
retab/types/documents/create_messages.py
retab/types/documents/edit.py
retab/types/documents/extract.py
retab/types/documents/parse.py
retab/types/documents/split.py
retab/types/edit/__init__.py
retab/types/edit/templates.py
retab/types/extractions/__init__.py
retab/types/extractions/types.py
retab/types/projects/__init__.py
retab/types/projects/metrics.py
retab/types/projects/model.py
retab/types/projects/predictions.py
retab/types/schemas/__init__.py
retab/types/schemas/chat.py
retab/types/schemas/generate.py
retab/types/schemas/layout.py
retab/types/schemas/model.py
retab/types/schemas/templates.py
retab/types/workflows/__init__.py
retab/types/workflows/model.py
retab/utils/__init__.py
retab/utils/display.py
retab/utils/hashing.py
retab/utils/json_schema.py
retab/utils/mime.py
retab/utils/stream_context_managers.py
retab-0.0.95.dist-info/METADATA
retab-0.0.95.dist-info/WHEEL
retab-0.0.95.dist-info/top_level.txt
retab-0.0.95.dist-info/RECORD
