Metadata-Version: 2.4
Name: retab
Version: 0.0.95
Summary: Retab official python library
Home-page: https://github.com/retab-dev/retab
Author: Retab
Author-email: contact@retab.com
Project-URL: Team website, https://retab.com
Classifier: Programming Language :: Python :: 3
Classifier: License :: OSI Approved :: MIT License
Classifier: Operating System :: POSIX :: Linux
Classifier: Operating System :: MacOS
Classifier: Intended Audience :: Science/Research
Requires-Python: >=3.6
Requires-Dist: Pillow
Requires-Dist: httpx
Requires-Dist: pydantic
Requires-Dist: pydantic_core
Requires-Dist: requests
Requires-Dist: backoff
Requires-Dist: numpy
Requires-Dist: rich
Requires-Dist: puremagic
Requires-Dist: fastapi
Requires-Dist: pycountry
Requires-Dist: phonenumbers
Requires-Dist: email_validator
Requires-Dist: python-stdnum
Requires-Dist: nanoid
Requires-Dist: openai
Requires-Dist: anthropic
Requires-Dist: google-genai
Requires-Dist: tiktoken
Requires-Dist: truststore
Dynamic: author
Dynamic: author-email
Dynamic: classifier
Dynamic: description
Dynamic: description-content-type
Dynamic: home-page
Dynamic: project-url
Dynamic: requires-dist
Dynamic: requires-python
Dynamic: summary
